cpdts/__init__.py
cpdts/fire_project/fire_create.py
cpdts/fire_project/templates/.gitattributes
cpdts/fire_project/templates/.gitignore
cpdts/fire_project/templates/README.md
cpdts/fire_project/templates/kiro/main.md
cpdts/fire_project/templates/pyproject.toml.j2
cpdts/fire_project/templates/src/__main__.py
cpdts/fire_project/templates/src/decorators/singleton.py
cpdts/fire_project/templates/src/init.py
cpdts/fire_project/templates/src/scripts/build.py
cpdts/fire_project/templates/src/scripts/ccx.py
cpdts/fire_project/templates/src/scripts/clean.py
cpdts/fire_project/templates/src/scripts/eol.py
cpdts/fire_project/templates/src/scripts/gitsync.py
cpdts/fire_project/templates/src/scripts/public.py
cpdts/fire_project/templates/vscode/extensions.json
cpdts/fire_project/templates/vscode/launch.json
cpdts/fire_project/templates/vscode/settings.json
cpdts/utils/genfile.py
cpdts-3.0.21.dist-info/WHEEL
cpdts-3.0.21.dist-info/entry_points.txt
cpdts-3.0.21.dist-info/METADATA
cpdts-3.0.21.dist-info/RECORD
