Metadata-Version: 2.3
Name: cpdts
Version: 3.0.21
Summary: 这个一个AI项目脚手架工具
Author: lipanpan
Author-email: lipanpan <lipanpanmail@163.com>
Requires-Dist: fire>=0.7.1
Requires-Dist: jinja2>=3.1.6
Requires-Dist: prompt-toolkit>=3.0.52
Requires-Dist: pyperclip>=1.11.0
Requires-Dist: requests>=2.32.5
Requires-Dist: toml>=0.10.2
Requires-Python: >=3.13
